featurelib/__init__.py
featurelib/__init__.pyi
featurelib/abc.py
featurelib/abc.pyi
featurelib-1.0.0.dist-info/licenses/LICENSE
featurelib-1.0.0.dist-info/METADATA
featurelib-1.0.0.dist-info/WHEEL
featurelib-1.0.0.dist-info/top_level.txt
featurelib-1.0.0.dist-info/RECORD
