Metadata-Version: 2.4
Name: featurelib
Version: 1.0.0
Summary: Separate complicated functionality from your class
Author-email: Soumyo Deep Gupta <deep.main.ac@gmail.com>
Maintainer-email: Soumyo Deep Gupta <deep.main.ac@gmail.com>
License-Expression: MIT
Project-URL: Documentation, https://d33p0st.in/docs/featurelib/
Project-URL: GitHub, https://github.com/d33p0st/featurelib
Classifier: Development Status :: 4 - Beta
Classifier: Programming Language :: Python :: 3.13
Classifier: Operating System :: MacOS :: MacOS X
Classifier: Operating System :: POSIX :: Linux
Classifier: Operating System :: Microsoft :: Windows
Classifier: Programming Language :: Python :: 3
Classifier: Programming Language :: Python :: 3 :: Only
Requires-Python: >=3.8
License-File: LICENSE
Dynamic: license-file
